python_mk_livestatus-0.4.dist-info/WHEEL
python_mk_livestatus-0.4.dist-info/METADATA
python_mk_livestatus-0.4.dist-info/DESCRIPTION.rst
python_mk_livestatus-0.4.dist-info/top_level.txt
python_mk_livestatus-0.4.dist-info/metadata.json
python_mk_livestatus-0.4.dist-info/RECORD
mk_livestatus/livestatus.py
mk_livestatus/__init__.py
