Metadata-Version: 2.0
Name: python-mk-livestatus
Version: 0.4
Summary: Helps to query MK livestatus and get results
Home-page: https://github.com/arthru/python-mk-livestatus
Author: Michael Fladischer
Author-email: michael@fladi.at
License: BSD
Download-URL: http://pypi.python.org/pypi/python-mk-livestatus
Platform: UNKNOWN
Classifier: Development Status :: 4 - Beta
Classifier: Intended Audience :: Developers
Classifier: Intended Audience :: System Administrators
Classifier: License :: OSI Approved :: BSD License
Classifier: Operating System :: OS Independent
Classifier: Programming Language :: Python
Classifier: Topic :: Software Development :: Libraries :: Python Modules
Classifier: Topic :: System :: Monitoring
